ffuflags/__init__.py
ffuflags/__main__.py
ffuflags-0.0.1.2.dist-info/LICENSE
ffuflags-0.0.1.2.dist-info/METADATA
ffuflags-0.0.1.2.dist-info/WHEEL
ffuflags-0.0.1.2.dist-info/top_level.txt
ffuflags-0.0.1.2.dist-info/RECORD
