Metadata-Version: 2.1
Name: ffuflags
Version: 0.0.1.2
Summary: Generate ffuf flag recommendations
Home-page: https://github.com/mikedesu/ffuflags
Author: darkmage
Author-email: darkmagex6+github@bugcrowdninja.com
Project-URL: Bug Tracker, https://github.com/mikedesu/ffuflags/issues
Classifier: Programming Language :: Python :: 3
Classifier: License :: OSI Approved :: MIT License
Classifier: Operating System :: OS Independent
Requires-Python: >=3.6
License-File: LICENSE
